matilda/__init__.py
matilda/config.py
matilda/metrics_helpers.py
matilda/api_routes/__init__.py
matilda/api_routes/api.py
matilda/api_routes/auth.py
matilda/api_routes/main.py
matilda/broker_deployment/__init__.py
matilda/broker_deployment/alpaca.py
matilda/broker_deployment/broker_interface.py
matilda/data_pipeline/TimeDataFrame.py
matilda/data_pipeline/__init__.py
matilda/data_pipeline/data_preparation_helpers.py
matilda/data_pipeline/db_crud.py
matilda/data_pipeline/db_tutorial.py
matilda/data_pipeline/object_model.py
matilda/data_pipeline/data_scapers/__init__.py
matilda/data_pipeline/data_scapers/asset_pricing_factors.py
matilda/data_pipeline/data_scapers/company_classification.py
matilda/data_pipeline/data_scapers/index_exchanges_tickers.py
matilda/data_pipeline/data_scapers/macroeconomic_data_scraper.py
matilda/data_pipeline/data_scapers/stock_prices_scraper.py
matilda/data_pipeline/data_scapers/financial_statements_scraper/__init__.py
matilda/data_pipeline/data_scapers/financial_statements_scraper/financial_statements_scraper.py
matilda/data_pipeline/data_scapers/financial_statements_scraper/html_scraper_sec_edgar.py
matilda/data_pipeline/data_scapers/financial_statements_scraper/macrotrend_scraper.py
matilda/data_pipeline/data_scapers/financial_statements_scraper/xbrl_scraper_sec_edgar.py
matilda/data_pipeline/data_streaming/__init__.py
matilda/data_pipeline/data_streaming/consumer.py
matilda/data_pipeline/data_streaming/producer.py
matilda/fundamental_analysis/__init__.py
matilda/fundamental_analysis/supporting_metrics.py
matilda/fundamental_analysis/accounting_ratios/__init__.py
matilda/fundamental_analysis/accounting_ratios/efficiency_ratios.py
matilda/fundamental_analysis/accounting_ratios/leverage_ratios.py
matilda/fundamental_analysis/accounting_ratios/liquidity_ratios.py
matilda/fundamental_analysis/accounting_ratios/market_value_ratios.py
matilda/fundamental_analysis/accounting_ratios/profitability_ratios.py
Quantropy-0.1.2.dist-info/LICENSE
Quantropy-0.1.2.dist-info/METADATA
Quantropy-0.1.2.dist-info/WHEEL
Quantropy-0.1.2.dist-info/top_level.txt
Quantropy-0.1.2.dist-info/RECORD
