Metadata-Version: 2.1
Name: Quantropy
Version: 0.1.2
Summary: Package to research, develop, and deploy investment strategies
Home-page: https://github.com/AlainDaccache/Quantropy
Author: Alain Daccache
Author-email: alaindacc@gmail.com
License: UNKNOWN
Platform: UNKNOWN
Classifier: Programming Language :: Python :: 3
Classifier: License :: OSI Approved :: MIT License
Classifier: Operating System :: OS Independent
Requires-Python: >=3.6
